AUTHORS.rst
CONTRIBUTING.rst
HISTORY.rst
LICENSE
MANIFEST.in
README.rst
requirements_dev.txt
setup.cfg
setup.py
docs/Makefile
docs/authors.rst
docs/conf.py
docs/contributing.rst
docs/history.rst
docs/index.rst
docs/installation.rst
docs/jpxlab.rst
docs/make.bat
docs/modules.rst
docs/readme.rst
docs/usage.rst
jpxlab/__init__.py
jpxlab/cli.py
jpxlab/jpxlab.py
jpxlab_test.egg-info/PKG-INFO
jpxlab_test.egg-info/SOURCES.txt
jpxlab_test.egg-info/dependency_links.txt
jpxlab_test.egg-info/entry_points.txt
jpxlab_test.egg-info/not-zip-safe
jpxlab_test.egg-info/requires.txt
jpxlab_test.egg-info/top_level.txt
tests/test_jpxlab.py