Metadata-Version: 2.1
Name: jpxlab-test
Version: 0.3.0
Summary: The data analysis sandbox for JPX
Home-page: https://github.com/AlpacaDB/jpxlab
Author: Yuki Hayashi
Author-email: yuki@alpaca.ai
License: MIT license
Keywords: jpxlab
Platform: UNKNOWN
Classifier: Development Status :: 2 - Pre-Alpha
Classifier: Intended Audience :: Developers
Classifier: License :: OSI Approved :: MIT License
Classifier: Natural Language :: English
Classifier: Programming Language :: Python :: 2
Classifier: Programming Language :: Python :: 2.7
Classifier: Programming Language :: Python :: 3
Classifier: Programming Language :: Python :: 3.4
Classifier: Programming Language :: Python :: 3.5
Classifier: Programming Language :: Python :: 3.6
Classifier: Programming Language :: Python :: 3.7
